{
  "schema_version": "country_sim_inputs_v1",
  "country": {
    "name": "Portugal",
    "iso2": "PT"
  },
  "inputs": {
    "rho": 0.88,
    "tau": 0.3475,
    "k": 0.3948863636363636,
    "C_people": 5100000.0,
    "P_people": 3600000.0,
    "C_m": 5.1,
    "P_m": 3.6,
    "u": 0.0642703,
    "pop_growth": 0.0109537,
    "aging_pp": 0.004191400000000023,
    "years": 80
  },
  "latest_observations_used": {
    "C": {
      "metric": "contributors_employed_people",
      "value": 5100000,
      "unit": "people",
      "period": {
        "date": "2023-12-31",
        "granularity": "year"
      },
      "notes": "Personas empleadas cotizantes a la seguridad social (proxy de cotizantes).",
      "sources": [
        {
          "source_id": "PT_INE_EMPLOYMENT_2023",
          "url": "https://www.ine.pt/xportal/xmain?xpid=INE&xpgid=ine_indicadores",
          "publisher": "Instituto Nacional de Estatística (INE)"
        }
      ]
    },
    "P": {
      "metric": "pensioners_people",
      "value": 3600000,
      "unit": "people",
      "period": {
        "date": "2023-12-31",
        "granularity": "year"
      },
      "notes": "Beneficiarios de pensiones públicas de vejez, invalidez y supervivencia del sistema de Seguridad Social.",
      "sources": [
        {
          "source_id": "PT_SEG_SOC_PENSIONERS_2023",
          "url": "https://www.seg-social.pt/estatisticas",
          "publisher": "Segurança Social – Ministério do Trabalho, Solidariedade e Segurança Social"
        }
      ]
    },
    "rho": {
      "metric": "replacement_rate_gross_full_career",
      "value": 0.88,
      "unit": "ratio",
      "period": {
        "date": "2023-11-01",
        "granularity": "publication_date"
      },
      "notes": "Tasa de reemplazo bruta obligatoria para trabajador medio con carrera completa (sistema público).",
      "sources": [
        {
          "source_id": "OECD_PAG_2023_PT_REPLACEMENT",
          "url": "https://www.oecd.org/en/publications/pensions-at-a-glance-2023_678055dd-en.html",
          "publisher": "OECD"
        }
      ]
    },
    "tau_components": [
      {
        "metric": "contribution_rate_pension_total",
        "value": 0.3475,
        "unit": "ratio",
        "period": {
          "date": "2024-01-01",
          "granularity": "year"
        },
        "notes": "Tipo total de cotización a la Seguridad Social para pensiones (empleador + trabajador).",
        "sources": [
          {
            "source_id": "PT_SOCSEC_CONTRIB_2024",
            "url": "https://www.seg-social.pt/taxas-contributivas",
            "publisher": "Segurança Social"
          }
        ]
      }
    ],
    "u": {
      "metric": "unemployment_rate_total_15plus_annual",
      "value": 0.0642703,
      "unit": "ratio",
      "period": {
        "date": "2024-12-31",
        "granularity": "year"
      },
      "notes": "Tasa de desempleo total (15+), 2024 (anual), serie OECD Infra-Annual Labor Statistics via FRED.",
      "sources": [
        {
          "source_id": "FRED_LRUNTTTTPTA156S",
          "url": "https://fred.stlouisfed.org/series/LRUNTTTTPTA156S",
          "publisher": "OECD via FRED (St. Louis Fed)"
        }
      ]
    },
    "pop_growth": {
      "metric": "population_growth_annual",
      "value": 0.0109537,
      "unit": "ratio",
      "period": {
        "date": "2024-12-31",
        "granularity": "year"
      },
      "notes": "Crecimiento anual de población (World Bank WDI) para 2024, vía FRED.",
      "sources": [
        {
          "source_id": "FRED_SPPOPGROWPRT",
          "url": "https://fred.stlouisfed.org/series/SPPOPGROWPRT",
          "publisher": "World Bank (WDI) via FRED (St. Louis Fed)"
        }
      ]
    },
    "share65": {
      "metric": "population_share_65_plus",
      "value": 0.2453065,
      "unit": "ratio",
      "period": {
        "date": "2024-12-31",
        "granularity": "year"
      },
      "notes": "Población 65+ como % del total (World Bank WDI / UN WPP), valor 2024, vía FRED.",
      "sources": [
        {
          "source_id": "FRED_SPPOP65UPTOZSPRT",
          "url": "https://fred.stlouisfed.org/series/SPPOP65UPTOZSPRT",
          "publisher": "World Bank (WDI) via FRED (St. Louis Fed)"
        }
      ]
    },
    "share65_prev": {
      "metric": "population_share_65_plus",
      "value": 0.2411151,
      "unit": "ratio",
      "period": {
        "date": "2023-12-31",
        "granularity": "year"
      },
      "notes": "Valor 2023 (para derivar Δ share 65+).",
      "sources": [
        {
          "source_id": "FRED_SPPOP65UPTOZSPRT",
          "url": "https://fred.stlouisfed.org/series/SPPOP65UPTOZSPRT",
          "publisher": "World Bank (WDI) via FRED (St. Louis Fed)"
        }
      ]
    },
    "aging_pp": {
      "metric": "delta_population_share_65_plus",
      "value": 0.004191400000000023,
      "unit": "ratio",
      "period": {
        "date": "2024-12-31",
        "granularity": "year"
      },
      "notes": "Δ share 65+ (en puntos porcentuales, almacenado como fracción): (2024 − 2023) / 100.",
      "sources": [
        {
          "source_id": "DERIVED_FROM_FRED_SPPOP65UPTOZSPRT",
          "url": "https://fred.stlouisfed.org/series/SPPOP65UPTOZSPRT",
          "publisher": "Derivado de World Bank (WDI) via FRED"
        }
      ]
    }
  },
  "observations": [
    {
      "metric": "pensioners_people",
      "value": 3600000,
      "unit": "people",
      "period": {
        "date": "2023-12-31",
        "granularity": "year"
      },
      "notes": "Beneficiarios de pensiones públicas de vejez, invalidez y supervivencia del sistema de Seguridad Social.",
      "sources": [
        {
          "source_id": "PT_SEG_SOC_PENSIONERS_2023",
          "url": "https://www.seg-social.pt/estatisticas",
          "publisher": "Segurança Social – Ministério do Trabalho, Solidariedade e Segurança Social"
        }
      ]
    },
    {
      "metric": "contributors_employed_people",
      "value": 5100000,
      "unit": "people",
      "period": {
        "date": "2023-12-31",
        "granularity": "year"
      },
      "notes": "Personas empleadas cotizantes a la seguridad social (proxy de cotizantes).",
      "sources": [
        {
          "source_id": "PT_INE_EMPLOYMENT_2023",
          "url": "https://www.ine.pt/xportal/xmain?xpid=INE&xpgid=ine_indicadores",
          "publisher": "Instituto Nacional de Estatística (INE)"
        }
      ]
    },
    {
      "metric": "contribution_rate_pension_total",
      "value": 0.3475,
      "unit": "ratio",
      "period": {
        "date": "2024-01-01",
        "granularity": "year"
      },
      "notes": "Tipo total de cotización a la Seguridad Social para pensiones (empleador + trabajador).",
      "sources": [
        {
          "source_id": "PT_SOCSEC_CONTRIB_2024",
          "url": "https://www.seg-social.pt/taxas-contributivas",
          "publisher": "Segurança Social"
        }
      ]
    },
    {
      "metric": "replacement_rate_gross_full_career",
      "value": 0.88,
      "unit": "ratio",
      "period": {
        "date": "2023-11-01",
        "granularity": "publication_date"
      },
      "notes": "Tasa de reemplazo bruta obligatoria para trabajador medio con carrera completa (sistema público).",
      "sources": [
        {
          "source_id": "OECD_PAG_2023_PT_REPLACEMENT",
          "url": "https://www.oecd.org/en/publications/pensions-at-a-glance-2023_678055dd-en.html",
          "publisher": "OECD"
        }
      ]
    },
    {
      "metric": "pension_expenditure_gdp_public",
      "value": 0.15,
      "unit": "ratio",
      "period": {
        "date": "2022-12-31",
        "granularity": "year"
      },
      "notes": "Gasto público en pensiones como porcentaje del PIB.",
      "sources": [
        {
          "source_id": "OECD_SOCX_PT_2022",
          "url": "https://www.oecd.org/social/expenditure.htm",
          "publisher": "OECD"
        }
      ]
    }
  ],
  "source": {
    "merged_schema_version": "1.0",
    "generated_from": "merge_country_jsons.py"
  },
  "missing_fields": []
}